face_cropping/__init__.py
face_cropping/cropping.py
face_cropping/cropping_simple.py
face_cropping-0.2.0.dist-info/LICENSE
face_cropping-0.2.0.dist-info/METADATA
face_cropping-0.2.0.dist-info/WHEEL
face_cropping-0.2.0.dist-info/top_level.txt
face_cropping-0.2.0.dist-info/RECORD
