Metadata-Version: 2.1
Name: face-cropping
Version: 0.2.0
Summary: face-cropping
Home-page: https://gitee.com/ren3016/face_cropping
Author: ren3016
Author-email: ren3016@qq.com
Project-URL: Documentation, https://gitee.com/ren3016/face_cropping
Project-URL: Source Code, https://gitee.com/ren3016/face_crop_code
Project-URL: Issues, https://gitee.com/ren3016/face_crop_code/issues
Keywords: face_cropping,photo,识别人脸,裁切人脸
Classifier: Programming Language :: Python :: 3.8
Classifier: License :: OSI Approved :: MIT License
Classifier: Operating System :: OS Independent
Requires-Python: >=3.8
License-File: LICENSE
Requires-Dist: opencv-python
Requires-Dist: dlib
